{
    "key": "group_64d647057a3a9",
    "title": "Component Image",
    "fields": [
        {
            "key": "field_64d64705686b6",
            "label": "Image First?",
            "name": "image_first",
            "aria-label": "",
            "type": "true_false",
            "instructions": "",
            "required": 0,
            "conditional_logic": 0,
            "wrapper": {
                "width": "",
                "class": "",
                "id": ""
            },
            "message": "Place image left, content right",
            "default_value": 0,
            "ui": 0,
            "ui_on_text": "",
            "ui_off_text": ""
        },
        {
            "key": "field_64d64757686b7",
            "label": "Image Sizing",
            "name": "image_sizing",
            "aria-label": "",
            "type": "radio",
            "instructions": "",
            "required": 0,
            "conditional_logic": 0,
            "wrapper": {
                "width": "",
                "class": "",
                "id": ""
            },
            "choices": {
                "image-cover": "Cover",
                "image-contain": "Contain"
            },
            "default_value": "image-cover",
            "return_format": "value",
            "allow_null": 0,
            "other_choice": 0,
            "layout": "vertical",
            "save_other_choice": 0
        },
        {
            "key": "field_64d6477f686b8",
            "label": "Card Image Part",
            "name": "card_image_part",
            "aria-label": "",
            "type": "image",
            "instructions": "",
            "required": 0,
            "conditional_logic": 0,
            "wrapper": {
                "width": "",
                "class": "",
                "id": ""
            },
            "return_format": "id",
            "library": "all",
            "min_width": "",
            "min_height": "",
            "min_size": "",
            "max_width": "",
            "max_height": "",
            "max_size": "",
            "mime_types": "",
            "preview_size": "medium"
        }
    ],
    "location": [
        [
            {
                "param": "post_type",
                "operator": "==",
                "value": "post"
            }
        ]
    ],
    "menu_order": 0,
    "position": "normal",
    "style": "default",
    "label_placement": "top",
    "instruction_placement": "label",
    "hide_on_screen": "",
    "active": true,
    "description": "",
    "show_in_rest": 0,
    "modified": 1691766048
}
